btjanaka/__init__.py
btjanaka-0.4.0.dist-info/LICENSE
btjanaka-0.4.0.dist-info/WHEEL
btjanaka-0.4.0.dist-info/METADATA
btjanaka-0.4.0.dist-info/RECORD
