Metadata-Version: 2.1
Name: btjanaka
Version: 0.4.0
Summary: Bryon Tjanaka in a Python package!
Home-page: https://btjanaka.net
License: MIT
Keywords: fun,awesome
Author: Bryon Tjanaka
Author-email: bryon@btjanaka.net
Requires-Python: >=3.7,<4.0
Classifier: Development Status :: 4 - Beta
Classifier: License :: OSI Approved :: MIT License
Classifier: Programming Language :: Python :: 3
Classifier: Programming Language :: Python :: 3.10
Classifier: Programming Language :: Python :: 3.7
Classifier: Programming Language :: Python :: 3.8
Classifier: Programming Language :: Python :: 3.9
Classifier: Topic :: Utilities
Project-URL: Repository, https://github.com/btjanaka/btjanaka-pypi
